Workbook

Sheet Sales Forecast
B2: Heartwood Sales Forecast
B3: Door Style | C3: Expected Sales | D3: Selling Price | E3: Expected Revenue
B4: Walnut - Arch | C4: 10000 | D4: 42 | E4: =C4*D4 -> 420000
B5: Walnut - Cathedral | C5: 9000 | D5: 45.9 | E5: =C5*D5 -> 413100
B6: Walnut - Shaker | C6: 15000 | D6: 38.15 | E6: =C6*D6 -> 572250
B7: Walnut - Slab | C7: 35000 | D7: 32.5 | E7: =C7*D7 -> 1137500
B8: Walnut - Beadboard | C8: 21000 | D8: 28.75 | E8: =C8*D8 -> 603750
B10: Total | E10: =SUM(E4:E8) -> 3146600

Sheet Production Budget Calc
A1: Budget Production (in units) | B1: = | C1: Budget Sales (in units) | D1: + | E1: Target ending finished goods inventory (in units) | F1: - | G1: Beginning finished goods inventory (in units)

Sheet Production Budget
B2: Heartwood Production Budget (in units)
C3: Walnut - Arch | D3: Walnut - Cathedral | E3: Walnut - Shaker | F3: Walnut - Slab | G3: Walnut - Beadboard
B4: Budgeted Sales | C4: =INDEX('Sales Forecast'!$C$4:$C$8,MATCH('Production Budget'!C3,'Sales Forecast'!$B$4:$B$8,0)) -> 10000 | D4: =INDEX('Sales Forecast'!$C$4:$C$8,MATCH('Production Budget'!D3,'Sales Forecast'!$B$4:$B$8,0)) -> 9000 | E4: =INDEX('Sales Forecast'!$C$4:$C$8,MATCH('Production Budget'!E3,'Sales Forecast'!$B$4:$B$8,0)) -> 15000 | F4: =INDEX('Sales Forecast'!$C$4:$C$8,MATCH('Production Budget'!F3,'Sales Forecast'!$B$4:$B$8,0)) -> 35000 | G4: =INDEX('Sales Forecast'!$C$4:$C$8,MATCH('Production Budget'!G3,'Sales Forecast'!$B$4:$B$8,0)) -> 21000
B5: (Plus) Target Ending Finished Goods Inventory | C5: =C4*5% -> 500 | D5: =D4*5% -> 450 | E5: =E4*5% -> 750 | F5: =F4*5% -> 1750 | G5: =G4*5% -> 1050
B6: Total Required Units | C6: =SUM(C4:C5) -> 10500 | D6: =SUM(D4:D5) -> 9450 | E6: =SUM(E4:E5) -> 15750 | F6: =SUM(F4:F5) -> 36750 | G6: =SUM(G4:G5) -> 22050
B7: (less) Beginning finished goods inventory | C7: =INDEX('Beginning Inventories Budget'!$C$4:$C$8,MATCH('Production Budget'!C3,'Beginning Inventories Budget'!$B$4:$B$8,0)) -> 800 | D7: =INDEX('Beginning Inventories Budget'!$C$4:$C$8,MATCH('Production Budget'!D3,'Beginning Inventories Budget'!$B$4:$B$8,0)) -> 2000 | E7: =INDEX('Beginning Inventories Budget'!$C$4:$C$8,MATCH('Production Budget'!E3,'Beginning Inventories Budget'!$B$4:$B$8,0)) -> 1500 | F7: =INDEX('Beginning Inventories Budget'!$C$4:$C$8,MATCH('Production Budget'!F3,'Beginning Inventories Budget'!$B$4:$B$8,0)) -> 500 | G7: =INDEX('Beginning Inventories Budget'!$C$4:$C$8,MATCH('Production Budget'!G3,'Beginning Inventories Budget'!$B$4:$B$8,0)) -> 1250
B8: Units to be Produced | C8: =C6-C7 -> 9700 | D8: =D6-D7 -> 7450 | E8: =E6-E7 -> 14250 | F8: =F6-F7 -> 36250 | G8: =G6-G7 -> 20800

Sheet Beginning Inventories Budget
B2: Heartwood Beginning Inventories Budget
C3: Beginning Inventory | D3: Direct Materials Cost Per Unit | E3: Direct Labor Cost Per Unit | F3: Manufacturing Overhead Cost per Unit | G3: Total Cost Per Unit of Output | H3: Total Cost of Beginning Finished Goods Inventory
B4: Walnut - Arch | C4: 800 | D4: =INDEX( 'Direct MaterialsBudget - All'!$C$4:$G$4,MATCH('Beginning Inventories Budget'!B4,'Direct MaterialsBudget - All'!$C$3:$G$3,0)) -> 26.4 | E4: =INDEX('Labor Cost- All'!$B$5:$F$5,MATCH('Beginning Inventories Budget'!B4,'Labor Cost- All'!$B$3:$F$3,0)) -> 5.85 | F4: =INDEX(Overhead!$G$4:$G$8,MATCH('Beginning Inventories Budget'!B4,Overhead!$B$4:$B$8,0))/INDEX(Overhead!$C$4:$C$8,MATCH('Beginning Inventories Budget'!B4,Overhead!$B$4:$B$8,0)) -> 2 | G4: =F4+D4+E5 -> 33.85 | H4: =G4*C4 -> 27080
B5: Walnut - Cathedral | C5: 2000 | D5: =INDEX( 'Direct MaterialsBudget - All'!$C$4:$G$4,MATCH('Beginning Inventories Budget'!B5,'Direct MaterialsBudget - All'!$C$3:$G$3,0)) -> 25 | E5: =INDEX('Labor Cost- All'!$B$5:$F$5,MATCH('Beginning Inventories Budget'!B5,'Labor Cost- All'!$B$3:$F$3,0)) -> 5.45 | F5: =INDEX(Overhead!$G$4:$G$8,MATCH('Beginning Inventories Budget'!B5,Overhead!$B$4:$B$8,0))/INDEX(Overhead!$C$4:$C$8,MATCH('Beginning Inventories Budget'!B5,Overhead!$B$4:$B$8,0)) -> 2 | G5: =F5+D5+E6 -> 31.98 | H5: =G5*C5 -> 63960
B6: Walnut - Shaker | C6: 1500 | D6: =INDEX( 'Direct MaterialsBudget - All'!$C$4:$G$4,MATCH('Beginning Inventories Budget'!B6,'Direct MaterialsBudget - All'!$C$3:$G$3,0)) -> 30.25 | E6: =INDEX('Labor Cost- All'!$B$5:$F$5,MATCH('Beginning Inventories Budget'!B6,'Labor Cost- All'!$B$3:$F$3,0)) -> 4.98 | F6: =INDEX(Overhead!$G$4:$G$8,MATCH('Beginning Inventories Budget'!B6,Overhead!$B$4:$B$8,0))/INDEX(Overhead!$C$4:$C$8,MATCH('Beginning Inventories Budget'!B6,Overhead!$B$4:$B$8,0)) -> 1.9 | G6: =F6+D6+E7 -> 39.34 | H6: =G6*C6 -> 59010
B7: Walnut - Slab | C7: 500 | D7: =INDEX( 'Direct MaterialsBudget - All'!$C$4:$G$4,MATCH('Beginning Inventories Budget'!B7,'Direct MaterialsBudget - All'!$C$3:$G$3,0)) -> 24 | E7: =INDEX('Labor Cost- All'!$B$5:$F$5,MATCH('Beginning Inventories Budget'!B7,'Labor Cost- All'!$B$3:$F$3,0)) -> 7.19 | F7: =INDEX(Overhead!$G$4:$G$8,MATCH('Beginning Inventories Budget'!B7,Overhead!$B$4:$B$8,0))/INDEX(Overhead!$C$4:$C$8,MATCH('Beginning Inventories Budget'!B7,Overhead!$B$4:$B$8,0)) -> 1.7 | G7: =F7+D7+E8 -> 32.72 | H7: =G7*C7 -> 16360
B8: Walnut - Beadboard | C8: 1250 | D8: =INDEX( 'Direct MaterialsBudget - All'!$C$4:$G$4,MATCH('Beginning Inventories Budget'!B8,'Direct MaterialsBudget - All'!$C$3:$G$3,0)) -> 18.6 | E8: =INDEX('Labor Cost- All'!$B$5:$F$5,MATCH('Beginning Inventories Budget'!B8,'Labor Cost- All'!$B$3:$F$3,0)) -> 7.02 | F8: =INDEX(Overhead!$G$4:$G$8,MATCH('Beginning Inventories Budget'!B8,Overhead!$B$4:$B$8,0))/INDEX(Overhead!$C$4:$C$8,MATCH('Beginning Inventories Budget'!B8,Overhead!$B$4:$B$8,0)) -> 1.8 | G8: =F8+D8+E9 -> 20.4 | H8: =G8*C8 -> 25500
H9: =SUM(H4:H8) -> 191910

Sheet BOM
B2: Heartwood Bill of Materials Walnut - Arch
B3: Part Number | C3: Part Name | D3: Cost per Part | E3: Quantity | F3: Total Cost for 1 Cabinet
B4: P27-1244 | C4: Panel | D4: 10.5 | E4: 1 | F4: =D4*E4 -> 10.5
B5: H14-7589 | C5: Handle | D5: 5.8 | E5: 1 | F5: =D5*E5 -> 5.8
B6: H99-3622 | C6: Hinges | D6: 2.3 | E6: 2 | F6: =D6*E6 -> 4.6
B7: L80-5429 | C7: Lever | D7: 1.5 | E7: 1 | F7: =D7*E7 -> 1.5
B8: L12-9014 | C8: Latch | D8: 4 | E8: 1 | F8: =D8*E8 -> 4

Sheet Direct Materials Budget - Arch
B2: Heartwood Direct Materials Budget Walnut - Arch
B3: Part Number | C3: Required Input | D3: Cost per Part | E3: Cost per Cabinet | F3: Expected Sales | H3: Total Cost
B4: P27-1244 | C4: =VLOOKUP(B4, BOM!$B$4:$F$8,4,0) -> 1 | D4: =VLOOKUP(B4,BOM!$B$4:$F$8,3,0) -> 10.5 | E4: =VLOOKUP(B4,BOM!$B$4:$F$8,5,0) -> 10.5 | F4: ='Sales Forecast'!$C$4 -> 10000 | H4: =F4*E4 -> 105000
B5: H14-7589 | C5: =VLOOKUP(B5, BOM!$B$4:$F$8,4,0) -> 1 | D5: =VLOOKUP(B5,BOM!$B$4:$F$8,3,0) -> 5.8 | E5: =VLOOKUP(B5,BOM!$B$4:$F$8,5,0) -> 5.8 | F5: ='Sales Forecast'!$C$4 -> 10000 | H5: =F5*E5 -> 58000
B6: H99-3622 | C6: =VLOOKUP(B6, BOM!$B$4:$F$8,4,0) -> 2 | D6: =VLOOKUP(B6,BOM!$B$4:$F$8,3,0) -> 2.3 | E6: =VLOOKUP(B6,BOM!$B$4:$F$8,5,0) -> 4.6 | F6: ='Sales Forecast'!$C$4 -> 10000 | H6: =F6*E6 -> 46000
B7: L80-5429 | C7: =VLOOKUP(B7, BOM!$B$4:$F$8,4,0) -> 1 | D7: =VLOOKUP(B7,BOM!$B$4:$F$8,3,0) -> 1.5 | E7: =VLOOKUP(B7,BOM!$B$4:$F$8,5,0) -> 1.5 | F7: ='Sales Forecast'!$C$4 -> 10000 | H7: =F7*E7 -> 15000
B8: L12-9014 | C8: =VLOOKUP(B8, BOM!$B$4:$F$8,4,0) -> 1 | D8: =VLOOKUP(B8,BOM!$B$4:$F$8,3,0) -> 4 | E8: =VLOOKUP(B8,BOM!$B$4:$F$8,5,0) -> 4 | F8: ='Sales Forecast'!$C$4 -> 10000 | H8: =F8*E8 -> 40000
E9: =SUM(E4:E8) -> 26.4 | H9: =SUM(H4:H8) -> 264000
B11: (Plus) Materials Cost for Target Ending Inventory (Ending Inventory Units X Total Direct Materials Required) | H11: =E9*'Production Budget'!C5 -> 13200
B12: (Less) Materials Cost for Beginning Inventory (Beg. Finished Goods Inventory X Total Direct Materials Required) | H12: =E9*'Beginning Inventories Budget'!C4 -> 21120
B14: Direct Materials to be used this Period | H14: =H9+H11-H12 -> 256080

Sheet Direct MaterialsBudget - All
B2: Heartwood Direct Materials Budget Walnut - All
C3: Walnut - Arch | D3: Walnut - Cathedral | E3: Walnut - Shaker | F3: Walnut - Slab | G3: Walnut - Beadboard
B4: Cost Per Unit | C4: ='Direct Materials Budget - Arch'!E9 -> 26.4 | D4: 25 | E4: 30.25 | F4: 24 | G4: 18.6
B5: Expected Sales | C5: =INDEX('Sales Forecast'!$C$4:$C$8,MATCH('Direct MaterialsBudget - All'!C3,'Sales Forecast'!$B$4:$B$8,0)) -> 10000 | D5: =INDEX('Sales Forecast'!$C$4:$C$8,MATCH('Direct MaterialsBudget - All'!D3,'Sales Forecast'!$B$4:$B$8,0)) -> 9000 | E5: =INDEX('Sales Forecast'!$C$4:$C$8,MATCH('Direct MaterialsBudget - All'!E3,'Sales Forecast'!$B$4:$B$8,0)) -> 15000 | F5: =INDEX('Sales Forecast'!$C$4:$C$8,MATCH('Direct MaterialsBudget - All'!F3,'Sales Forecast'!$B$4:$B$8,0)) -> 35000 | G5: =INDEX('Sales Forecast'!$C$4:$C$8,MATCH('Direct MaterialsBudget - All'!G3,'Sales Forecast'!$B$4:$B$8,0)) -> 21000
B6: Total Direct Materials Required | C6: =C4*C5 -> 264000 | D6: =D4*D5 -> 225000 | E6: =E4*E5 -> 453750 | F6: =F4*F5 -> 840000 | G6: =G4*G5 -> 390600
B8: Target Ending Inventory | C8: =INDEX('Production Budget'!$C$5:$G$5,MATCH('Direct MaterialsBudget - All'!C3,'Production Budget'!$C$3:$G$3,0)) -> 500 | D8: =INDEX('Production Budget'!$C$5:$G$5,MATCH('Direct MaterialsBudget - All'!D3,'Production Budget'!$C$3:$G$3,0)) -> 450 | E8: =INDEX('Production Budget'!$C$5:$G$5,MATCH('Direct MaterialsBudget - All'!E3,'Production Budget'!$C$3:$G$3,0)) -> 750 | F8: =INDEX('Production Budget'!$C$5:$G$5,MATCH('Direct MaterialsBudget - All'!F3,'Production Budget'!$C$3:$G$3,0)) -> 1750 | G8: =INDEX('Production Budget'!$C$5:$G$5,MATCH('Direct MaterialsBudget - All'!G3,'Production Budget'!$C$3:$G$3,0)) -> 1050
B9: (Plus) Materials Cost for Target Ending Inventory | C9: =C8*C4 -> 13200 | D9: =D8*D4 -> 11250 | E9: =E8*E4 -> 22687.5 | F9: =F8*F4 -> 42000 | G9: =G8*G4 -> 19530
B10: Beginning Inventory | C10: =INDEX('Beginning Inventories Budget'!$C$4:$C$8,MATCH('Direct MaterialsBudget - All'!C3,'Beginning Inventories Budget'!$B$4:$B$8,0)) -> 800 | D10: =INDEX('Beginning Inventories Budget'!$C$4:$C$8,MATCH('Direct MaterialsBudget - All'!D3,'Beginning Inventories Budget'!$B$4:$B$8,0)) -> 2000 | E10: =INDEX('Beginning Inventories Budget'!$C$4:$C$8,MATCH('Direct MaterialsBudget - All'!E3,'Beginning Inventories Budget'!$B$4:$B$8,0)) -> 1500 | F10: =INDEX('Beginning Inventories Budget'!$C$4:$C$8,MATCH('Direct MaterialsBudget - All'!F3,'Beginning Inventories Budget'!$B$4:$B$8,0)) -> 500 | G10: =INDEX('Beginning Inventories Budget'!$C$4:$C$8,MATCH('Direct MaterialsBudget - All'!G3,'Beginning Inventories Budget'!$B$4:$B$8,0)) -> 1250
B11: (Less) Materials Cost for Beginning Inventory | C11: =C10*C4 -> 21120 | D11: =D10*D4 -> 50000 | E11: =E10*E4 -> 45375 | F11: =F10*F4 -> 12000 | G11: =G10*G4 -> 23250
B13: Direct Materials to be used this Period | C13: =C9+C6-C11 -> 256080 | D13: =D9+D6-D11 -> 186250 | E13: =E9+E6-E11 -> 431062.5 | F13: =F9+F6-F11 -> 870000 | G13: =G9+G6-G11 -> 386880
C20: =MAX(C13:G13) -> 870000 | D20: =_xlfn.XLOOKUP(C20,C13:G13,C3:G3) -> Walnut - Slab

Sheet Route Sheet & Labor Cost- Arch
B2: Heartwood Direct Manufacturing Labor Costs Budget Walnut - Arch
B3: Work Station | C3: Activity | D3: Minutes Required (for 1 unit) | E3: Hourly Wage Rate | F3: Labor Cost per Unit | G3: Units to Produce | H3: Total Labor Cost
B4: 1 | C4: Trim & Sand Door | D4: 8 | E4: 17 | F4: =(D4/60)*E4 -> 2.2666667 | G4: 9700 | H4: =F4*G4 -> 21986.667
B5: 2 | C5: Attach handle | D5: 5 | E5: 15 | F5: =(D5/60)*E5 -> 1.25 | G5: 9700 | H5: =F5*G5 -> 12125
B6: 3 | C6: Attach lever and Hinges | D6: 7 | E6: 20 | F6: =(D6/60)*E6 -> 2.3333333 | G6: 9700 | H6: =F6*G6 -> 22633.333
B7: Total | D7: =SUM(D4:D6) -> 20 | F7: =SUM(F4:F6) -> 5.85 | G7: 9700 | H7: =F7*G7 -> 56745

Sheet Labor Cost- All
A2: Heartwood Direct Labor Budget
B3: Walnut - Arch | C3: Walnut - Cathedral | D3: Walnut - Shaker | E3: Walnut - Slab | F3: Walnut - Beadboard
A4: Units to Produce | B4: =INDEX('Production Budget'!$C$8:$G$8,MATCH('Labor Cost- All'!B3,'Production Budget'!$C$3:$G$3,0)) -> 9700 | C4: =INDEX('Production Budget'!$C$8:$G$8,MATCH('Labor Cost- All'!C3,'Production Budget'!$C$3:$G$3,0)) -> 7450 | D4: =INDEX('Production Budget'!$C$8:$G$8,MATCH('Labor Cost- All'!D3,'Production Budget'!$C$3:$G$3,0)) -> 14250 | E4: =INDEX('Production Budget'!$C$8:$G$8,MATCH('Labor Cost- All'!E3,'Production Budget'!$C$3:$G$3,0)) -> 36250 | F4: =INDEX('Production Budget'!$C$8:$G$8,MATCH('Labor Cost- All'!F3,'Production Budget'!$C$3:$G$3,0)) -> 20800
A5: Labor Cost per Unit | B5: ='Route Sheet & Labor Cost- Arch'!F7 -> 5.85 | C5: 5.45 | D5: 4.98 | E5: 7.19 | F5: 7.02
A6: Total Labor Cost | B6: =B4*B5 -> 56745 | C6: =C4*C5 -> 40602.5 | D6: =D4*D5 -> 70965 | E6: =E4*E5 -> 260637.5 | F6: =F4*F5 -> 146016
C11: =MIN(B5:F5) -> 4.98

Sheet Overhead
B2: Heartwood Manufacturing Overhead
C3: Units to Produce | D3: Direct Labor Minutes Required for 1 unit | E3: Direct Labor Hours Required for 1 unit | F3: Predetermined Overhead Rate | G3: Manufacturing Overhead
B4: Walnut - Arch | C4: =INDEX('Production Budget'!$C$8:$G$8,MATCH(Overhead!B4,'Production Budget'!$C$3:$G$3,0)) -> 9700 | D4: 20 | E4: =D4/60 -> 0.33333333 | F4: 6 | G4: =C4*E4*F4 -> 19400
B5: Walnut - Cathedral | C5: =INDEX('Production Budget'!$C$8:$G$8,MATCH(Overhead!B5,'Production Budget'!$C$3:$G$3,0)) -> 7450 | D5: 20 | E5: =D5/60 -> 0.33333333 | F5: 6 | G5: =C5*E5*F5 -> 14900
B6: Walnut - Shaker | C6: =INDEX('Production Budget'!$C$8:$G$8,MATCH(Overhead!B6,'Production Budget'!$C$3:$G$3,0)) -> 14250 | D6: 19 | E6: =D6/60 -> 0.31666667 | F6: 6 | G6: =C6*E6*F6 -> 27075
B7: Walnut - Slab | C7: =INDEX('Production Budget'!$C$8:$G$8,MATCH(Overhead!B7,'Production Budget'!$C$3:$G$3,0)) -> 36250 | D7: 17 | E7: =D7/60 -> 0.28333333 | F7: 6 | G7: =C7*E7*F7 -> 61625
B8: Walnut - Beadboard | C8: =INDEX('Production Budget'!$C$8:$G$8,MATCH(Overhead!B8,'Production Budget'!$C$3:$G$3,0)) -> 20800 | D8: 18 | E8: =D8/60 -> 0.3 | F8: 6 | G8: =C8*E8*F8 -> 37440
B9: Total Manufacturing Overhead | G9: =SUM(G4:G8) -> 160440

Sheet Ending Inventories Budget
B2: Heartwood Ending Inventories Budget
C3: Ending Inventory | D3: Direct Materials Cost Per Unit | E3: Direct Labor Cost Per Unit | F3: Manufacturing Overhead Cost per Unit | G3: Total Cost Per Unit of Output | H3: Total Cost of Ending Finished Goods Inventory
B4: Walnut - Arch | C4: =INDEX('Production Budget'!$C$5:$G$5,MATCH('Ending Inventories Budget'!B4,'Production Budget'!$C$3:$G$3,0)) -> 500 | D4: ='Beginning Inventories Budget'!D4 -> 26.4 | E4: ='Beginning Inventories Budget'!E4 -> 5.85 | F4: ='Beginning Inventories Budget'!F4 -> 2 | G4: =SUM(D4:F4) -> 34.25 | H4: =G4*C4 -> 17125
B5: Walnut - Cathedral | C5: =INDEX('Production Budget'!$C$5:$G$5,MATCH('Ending Inventories Budget'!B5,'Production Budget'!$C$3:$G$3,0)) -> 450 | D5: ='Beginning Inventories Budget'!D5 -> 25 | E5: ='Beginning Inventories Budget'!E5 -> 5.45 | F5: ='Beginning Inventories Budget'!F5 -> 2 | G5: =SUM(D5:F5) -> 32.45 | H5: =G5*C5 -> 14602.5
B6: Walnut - Shaker | C6: =INDEX('Production Budget'!$C$5:$G$5,MATCH('Ending Inventories Budget'!B6,'Production Budget'!$C$3:$G$3,0)) -> 750 | D6: ='Beginning Inventories Budget'!D6 -> 30.25 | E6: ='Beginning Inventories Budget'!E6 -> 4.98 | F6: ='Beginning Inventories Budget'!F6 -> 1.9 | G6: =SUM(D6:F6) -> 37.13 | H6: =G6*C6 -> 27847.5
B7: Walnut - Slab | C7: =INDEX('Production Budget'!$C$5:$G$5,MATCH('Ending Inventories Budget'!B7,'Production Budget'!$C$3:$G$3,0)) -> 1750 | D7: ='Beginning Inventories Budget'!D7 -> 24 | E7: ='Beginning Inventories Budget'!E7 -> 7.19 | F7: ='Beginning Inventories Budget'!F7 -> 1.7 | G7: =SUM(D7:F7) -> 32.89 | H7: =G7*C7 -> 57557.5
B8: Walnut - Beadboard | C8: =INDEX('Production Budget'!$C$5:$G$5,MATCH('Ending Inventories Budget'!B8,'Production Budget'!$C$3:$G$3,0)) -> 1050 | D8: ='Beginning Inventories Budget'!D8 -> 18.6 | E8: ='Beginning Inventories Budget'!E8 -> 7.02 | F8: ='Beginning Inventories Budget'!F8 -> 1.8 | G8: =SUM(D8:F8) -> 27.42 | H8: =G8*C8 -> 28791
B9: Total Ending Inventory Cost | D9: ='Beginning Inventories Budget'!D9 -> 0 | G9: =SUM(D9:F9) -> 0 | H9: =SUM(H4:H8) -> 145923.5

Sheet COGS Budget
B2: Heartwood Cost of Goods Sold Budget
B4: Beginning Finished Goods Inventory | D4: ='Beginning Inventories Budget'!H9 -> 191910
B5: Direct Materials Used | C5: =SUM('Direct MaterialsBudget - All'!C13:G13) -> 2130272.5
B6: Direct Manufacturing Labor | C6: =SUM('Labor Cost- All'!B6:F6) -> 574966
B7: Direct Manufacturing Overhead | C7: =Overhead!G9 -> 160440
B8: Cost of Goods Manufactured | D8: =SUM(C5:C7) -> 2865678.5
B9: Costs of Goods Available for Sale | D9: =D4+D8 -> 3057588.5
B10: (Less) Ending Finished Goods Inventory | D10: ='Ending Inventories Budget'!H9 -> 145923.5
B11: Cost of Goods Sold | D11: =D9-D10 -> 2911665

Sheet Non-Manufacturing Costs
B2: Heartwood Operating Costs Budget
C3: Units Sold | D3: Variable | E3: Fixed | F3: Total Cost
B4: Product Development | C4: =SUM('Sales Forecast'!$C$4:$C$8) -> 90000 | E4: 40000 | F4: =SUM(D4:E4) -> 40000
B5: Marketing | C5: =SUM('Sales Forecast'!$C$4:$C$8) -> 90000 | E5: 80000 | F5: =SUM(D5:E5) -> 80000
B6: Distribution | C6: =SUM('Sales Forecast'!$C$4:$C$8) -> 90000 | D6: 35000 | F6: =SUM(D6:E6) -> 35000
B7: Total Operating Costs | F7: =SUM(F4:F6) -> 155000

Sheet Flexible Budget
B2: Champion Budget - Game Day Hoodies
C3: Per Unit | D3: Static Budget | E3: -20% | F3: -10% | G3: +10% | H3: +20%
B4: Units Sold | D4: 20000 | E4: =$D$4+($D$4*E3) -> 16000 | F4: =$D$4+($D$4*F3) -> 18000 | G4: =$D$4+($D$4*G3) -> 22000 | H4: =$D$4+($D$4*H3) -> 24000
B5: Revenue | C5: 50 | D5: =D4*$C$5 -> 1000000 | E5: =E4*$C$5 -> 800000 | F5: =F4*$C$5 -> 900000 | G5: =G4*$C$5 -> 1100000 | H5: =H4*$C$5 -> 1200000
B6: Variable Costs
B7: Direct Material | C7: 8 | D7: =D4*$C$7 -> 160000 | E7: =E4*$C$7 -> 128000 | F7: =F4*$C$7 -> 144000 | G7: =G4*$C$7 -> 176000 | H7: =H4*$C$7 -> 192000
B8: Direct Labor | C8: 4 | D8: =D4*$C$8 -> 80000 | E8: =E4*$C$8 -> 64000 | F8: =F4*$C$8 -> 72000 | G8: =G4*$C$8 -> 88000 | H8: =H4*$C$8 -> 96000
B9: Variable Manufacturing Overhead | C9: 2.5 | D9: =D4*$C$9 -> 50000 | E9: =E4*$C$9 -> 40000 | F9: =F4*$C$9 -> 45000 | G9: =G4*$C$9 -> 55000 | H9: =H4*$C$9 -> 60000
B10: Variable SG&A Costs | C10: 2.25 | D10: =D4*$C$10 -> 45000 | E10: =E4*$C$10 -> 36000 | F10: =F4*$C$10 -> 40500 | G10: =G4*$C$10 -> 49500 | H10: =H4*$C$10 -> 54000
B11: Total variable Costs | C11: 16.75 | D11: =D4*$C$11 -> 335000 | E11: =E4*$C$11 -> 268000 | F11: =F4*$C$11 -> 301500 | G11: =G4*$C$11 -> 368500 | H11: =H4*$C$11 -> 402000
B12: Contribution Margin | D12: =D5-D11 -> 665000 | E12: =E5-E11 -> 532000 | F12: =F5-F11 -> 598500 | G12: =G5-G11 -> 731500 | H12: =H5-H11 -> 798000
B13: Fixed Costs
B14: Fixed Manufacturing Overhead | C14: Fixed | D14: 100000 | E14: 100000 | F14: 100000 | G14: 100000 | H14: 100000
B15: Fixed SG&A Costs | C15: Fixed | D15: 50000 | E15: 50000 | F15: 50000 | G15: 50000 | H15: 50000
B16: Total Fixed Costs | D16: =SUM(D14:D15) -> 150000 | E16: =SUM(E14:E15) -> 150000 | F16: =SUM(F14:F15) -> 150000 | G16: =SUM(G14:G15) -> 150000 | H16: =SUM(H14:H15) -> 150000
B17: Operating Income | D17: =D12-D16 -> 515000 | E17: =E12-E16 -> 382000 | F17: =F12-F16 -> 448500 | G17: =G12-G16 -> 581500 | H17: =H12-H16 -> 648000

Sheet Scenario Summary
B2: Scenario Summary
D3: Current Values: | E3: Scenario 1 - 10% Sales Decrease | F3: Scenario 2 - Direct Materials 1% Discount
E4: Created by Heartwood Management Accountants | F4: Created by Heartwood Management Accountants
B5: Changing Cells:
C6: $B$4 | D6: 18000 | E6: 16200 | F6: 18000
C7: $B$5 | D7: 13000 | E7: 11700 | F7: 13000
C8: $B$6 | D8: 25000 | E8: 22500 | F8: 25000
C9: $B$7 | D9: 22000 | E9: 19800 | F9: 22000
C10: $B$8 | D10: 30000 | E10: 27000 | F10: 30000
C11: $D$4 | D11: 21.87 | E11: 21.87 | F11: 19.9
C12: $D$5 | D12: 22.12 | E12: 22.12 | F12: 21.9
C13: $D$6 | D13: 19.18 | E13: 19.18 | F13: 18.99
C14: $D$7 | D14: 17.56 | E14: 17.56 | F14: 17.38
C15: $D$8 | D15: 14.1 | E15: 14.1 | F15: 13.96
B16: Result Cells:
C17: $F$9 | D17: 415870 | E17: 374283 | F17: 467100
B18: Notes: Current Values column represents values of changing cells at
B19: time Scenario Summary Report was created. Changing cells for each
B20: scenario are highlighted in gray.
E23: =(D17-E17)/D17 -> 0.1
E25: =(D17-F17)/D17 -> -0.12318753

Sheet Pro Forma Income Statement
B2: Heartwood Pro Forma Operating Income Statement
B4: Revenue | C4: ='Sales Forecast'!E10 -> 3146600
B5: Cost of Goods Sold | C5: 2918470
B6: Gross Margin | C6: =C4-C5 -> 228130
B7: Operating Costs
B8: Production Development | C8: ='Non-Manufacturing Costs'!F4 -> 40000
B9: Marketing Costs | C9: ='Non-Manufacturing Costs'!F5 -> 80000
B10: Distribution Costs | C10: ='Non-Manufacturing Costs'!F6 -> 35000
B11: Operating Income | C11: =C6-(SUM(C8:C10)) -> 73130

Sheet Pro Forma Operating Income Stmt
B2: Heartwood Pro Forma Operating Income Statement
C3: Units Sold | D3: Sales Price | E3: Direct Materials Cost | F3: Direct Labor Cost | G3: Budgeted Operating Income
B4: Pine - Arch
B5: Pine - Cathedral
B6: Pine - Shaker
B7: Pine - Slab
B8: Pine - Beadboard
G9: =SUM(G4:G8) -> 0
